lineax/__init__.py
lineax/_custom_types.py
lineax/_misc.py
lineax/_norm.py
lineax/_operator.py
lineax/_solution.py
lineax/_solve.py
lineax/_tags.py
lineax/_solver/__init__.py
lineax/_solver/bicgstab.py
lineax/_solver/cg.py
lineax/_solver/cholesky.py
lineax/_solver/diagonal.py
lineax/_solver/gmres.py
lineax/_solver/lu.py
lineax/_solver/misc.py
lineax/_solver/qr.py
lineax/_solver/svd.py
lineax/_solver/triangular.py
lineax/_solver/tridiagonal.py
lineax/internal/__init__.py
lineax-0.0.8.dist-info/METADATA
lineax-0.0.8.dist-info/WHEEL
lineax-0.0.8.dist-info/licenses/LICENSE
lineax-0.0.8.dist-info/RECORD
