Metadata-Version: 2.4
Name: lineax
Version: 0.0.8
Summary: Linear solvers in JAX and Equinox.
Project-URL: repository, https://github.com/google/lineax
Author-email: Jason Rader <raderjason@outlook.com>, Patrick Kidger <contact@kidger.site>
License:                                  Apache License
License-File: LICENSE
Keywords: deep-learning,equinox,jax,least-squares,linear-solvers,neural-networks,numerical-methods
Classifier: Development Status :: 3 - Alpha
Classifier: Intended Audience :: Developers
Classifier: Intended Audience :: Financial and Insurance Industry
Classifier: Intended Audience :: Information Technology
Classifier: Intended Audience :: Science/Research
Classifier: License :: OSI Approved :: Apache Software License
Classifier: Natural Language :: English
Classifier: Programming Language :: Python :: 3
Classifier: Topic :: Scientific/Engineering :: Artificial Intelligence
Classifier: Topic :: Scientific/Engineering :: Information Analysis
Classifier: Topic :: Scientific/Engineering :: Mathematics
Requires-Python: ~=3.10
Requires-Dist: equinox>=0.11.10
Requires-Dist: jax>=0.4.38
Requires-Dist: jaxtyping>=0.2.24
Requires-Dist: typing-extensions>=4.5.0
Provides-Extra: docs
Requires-Dist: hippogriffe==0.2.0; extra == 'docs'
Requires-Dist: mkdocs-include-exclude-files==0.1.0; extra == 'docs'
Requires-Dist: mkdocs-ipynb==0.1.0; extra == 'docs'
Requires-Dist: mkdocs-material==9.6.7; extra == 'docs'
Requires-Dist: mkdocs==1.6.1; extra == 'docs'
Requires-Dist: mkdocstrings[python]==0.28.3; extra == 'docs'
Requires-Dist: pymdown-extensions==10.14.3; extra == 'docs'
